{
    "lecturers": [
      {
        "id": 1,
        "name": "Jan",
        "surname": "Kowalski",
        "phone": "111-111-111",
        "email": "jankowalski@pl",
        "course": ["JavaScript", "Java"],
        "localization":["Warszawa"],
        "mode":["stacjonarny"],
        "comments": "Dobry gość"
      },
      {
        "id": 2,
        "name": "Janusz",
        "surname": "Polak",
        "phone": "222-222-222",
        "email": "januszpolak@pl",
        "course": ["Java"],
        "localization":["Wrocław"],
        "mode":["weekendowy"],
        "comments": "Może być"
      },
      {
        "id": 3,
        "name": "Grażyna",
        "surname": "Polka",
        "phone": "333-333-333",
        "email": "grażynap@pl",
        "course": ["PHP"],
        "localization":["Poznań"],
        "mode":["stacjonarny"],
        "comments": "Super!"
        },
        {
        "id": 4,
        "name": "Mariusz",
        "surname": "Kowal",
        "phone": "444-444-444",
        "email": "mariuszkow@pl",
        "course": ["Python"],
        "localization":["Katowice"],
        "mode":["weekendowy"],
        "comments": "Umawiać wcześniej"
        },
        {
        "id": 5,
        "name": "Bill",
        "surname": "Gates",
        "phone": "555-555-555",
        "email": "billybill@pl",
        "course": ["Java", "JavaScript", "Python"],
        "localization":["Warszawa", "Kraków", "Katowice"],
        "mode":["stacjonarny"],
        "comments": "Najlepiej!"
        },
        {
        "id": 6,
        "name": "Tomasz",
        "surname": "Szatan",
        "phone": "666-666-666",
        "email": "szatan@pl",
        "course": ["UX Design"],
        "localization":["Kraków"],
        "mode":["stacjonarny"],
        "comments": "Kursanci go lubią"
        },
        {
        "id": 7,
        "name": "Mariola",
        "surname": "Bagińska",
        "phone": "777-777-777",
        "email": "testymario@pl",
        "course": ["Tester Manualny"],
        "localization":["Warszawa"],
        "mode":["stacjonarny"],
        "comments": ""
         },
         {
         "id": 8,
         "name": "Paweł",
         "surname": "Pawłowski",
         "phone": "888-888-888",
         "email": "pawpaw@pl",
         "course": ["Tester Automatyzujący"],
         "localization":["Poznań"],
         "mode":["weekendowy"],
         "comments": "Nowy, do sprawdzenia"
        },
        {
         "id": 9,
         "name": "Mirosław",
         "surname": "Janowski",
         "phone": "999-999-999",
         "email": "mirojanowski@pl",
         "course": ["JavaScript"],
         "localization":["Warszawa"],
         "mode":["stacjonarny"],
         "comments": "5 lat doświadczenia"
         },
         {
          "id": 10,
          "name": "Monika",
          "surname": "Monikowska",
          "phone": "101-101-101",
          "email": "monikowskam@pl",
          "course": ["JavaScript"],
          "localization":["Poznań", "Wrocław"],
          "mode":["weekendowy"],
          "comments": "Super!"
        },
        {
          "id": 11,
          "name": "Jan",
          "surname": "Kowalczyk",
          "phone": "345-678-111",
          "email": "jankowalczyk@pl",
          "course": ["UX Design", "JavaScript"],
          "localization":["Warszawa", "Wrocław"],
          "mode":["stacjonarny"],
          "comments": "Super opinie."
        },
        {
          "id": 12,
          "name": "Tomasz",
          "surname": "Dizajner",
          "phone": "666-666-666",
          "email": "tomdiz@pl",
          "course": ["UX Design"],
          "localization":["Kraków", "Poznań","Warszawa","Wrocław","Katowice"],
          "mode":["stacjonarny"],
          "comments": "Kursanci go lubią"
          }
    ],
         "lectures": [
          { "id": 1,
            "date": "2019-09-30",
            "lecturerId": 1
          },
          { "id": 2,
            "date": "2019-10-12",
            "lecturerId": 2
          },
          {
            "id": 3,
            "date": "2019-09-28",
            "lecturerId": 3
          },
          {
            "id": 4,
            "date": "2019-10-05",
            "lecturerId": 4
          },
          {
            "id": 5,
            "date": "2019-09-30",
            "lecturerId": 5
          },
          {"id": 5,
            "date": "2019-10-01",
            "lecturerId": 5
          },
          {"id": 5,
            "date": "2019-10-02",
            "lecturerId": 5
          },
          {"id": 5,
            "date": "2019-10-03",
            "lecturerId": 5
          },
          {"id": 5,
            "date": "2019-10-04",
            "lecturerId": 5
          },
          {
            "id": 6,
            "date": "2019-10-28",
            "lecturerId": 6
          },
          {
            "id": 6,
            "date": "2019-10-29",
            "lecturerId": 6
          },
          {
            "id": 6,
            "date": "2019-10-30",
            "lecturerId": 6
          },
          {
            "id": 6,
            "date": "2019-10-31",
            "lecturerId": 6
          },
          {
            "id": 6,
            "date": "2019-11-01",
            "lecturerId": 6
          },
          {
            "id": 7,
            "date": "2019-10-07",
            "lecturerId": 7
          },
          {
            "id": 8,
            "date": "2019-10-04",
            "lecturerId": 8
          },
          {
            "id": 9,
            "date": "2019-10-14",
            "lecturerId": 9
          },
          {
            "id": 10,
            "date": "2019-10-12",
            "lecturerId": 10
          },
          {
            "id": 10,
            "date": "2019-10-13",
            "lecturerId": 10
          },
          { "id": 11,
            "date": "2019-10-21",
            "lecturerId": 11
          },
          { "id": 11,
            "date": "2019-10-22",
            "lecturerId": 11
          },
          { "id": 11,
            "date": "2019-10-23",
            "lecturerId": 11
          },
          { "id": 11,
            "date": "2019-10-24",
            "lecturerId": 11
          },
          { "id": 11,
            "date": "2019-10-25",
            "lecturerId": 11
          }
         ]
  }

